qsamplehello.py
qsamplehellor-0.0.1.dist-info/METADATA
qsamplehellor-0.0.1.dist-info/WHEEL
qsamplehellor-0.0.1.dist-info/top_level.txt
qsamplehellor-0.0.1.dist-info/RECORD
